MANIFEST.in
Readme.md
dataproviders.txt
dev-requirements.txt
licence.txt
requirements.txt
setup.cfg
setup.py
pandas_ml_quant_data_provider/__init__.py
pandas_ml_quant_data_provider/fetch.py
pandas_ml_quant_data_provider/provider.py
pandas_ml_quant_data_provider.egg-info/PKG-INFO
pandas_ml_quant_data_provider.egg-info/SOURCES.txt
pandas_ml_quant_data_provider.egg-info/dependency_links.txt
pandas_ml_quant_data_provider.egg-info/requires.txt
pandas_ml_quant_data_provider.egg-info/top_level.txt
pandas_ml_quant_data_provider/__pycache__/__init__.cpython-37.pyc
pandas_ml_quant_data_provider/__pycache__/__init__.cpython-38.pyc
pandas_ml_quant_data_provider/__pycache__/fetch.cpython-37.pyc
pandas_ml_quant_data_provider/__pycache__/fetch.cpython-38.pyc
pandas_ml_quant_data_provider/__pycache__/provider.cpython-37.pyc
pandas_ml_quant_data_provider/__pycache__/provider.cpython-38.pyc
pandas_ml_quant_data_provider/datafetching/__init__.py
pandas_ml_quant_data_provider/datafetching/fetch_cryptocompare.py
pandas_ml_quant_data_provider/datafetching/fetch_fred.py
pandas_ml_quant_data_provider/datafetching/fetch_investing.py
pandas_ml_quant_data_provider/datafetching/fetch_yahoo.py
pandas_ml_quant_data_provider/datafetching/read_ts_file.py
pandas_ml_quant_data_provider/datafetching/__pycache__/__init__.cpython-37.pyc
pandas_ml_quant_data_provider/datafetching/__pycache__/__init__.cpython-38.pyc
pandas_ml_quant_data_provider/datafetching/__pycache__/fetch_cryptocompare.cpython-37.pyc
pandas_ml_quant_data_provider/datafetching/__pycache__/fetch_cryptocompare.cpython-38.pyc
pandas_ml_quant_data_provider/datafetching/__pycache__/fetch_fred.cpython-37.pyc
pandas_ml_quant_data_provider/datafetching/__pycache__/fetch_fred.cpython-38.pyc
pandas_ml_quant_data_provider/datafetching/__pycache__/fetch_investing.cpython-37.pyc
pandas_ml_quant_data_provider/datafetching/__pycache__/fetch_investing.cpython-38.pyc
pandas_ml_quant_data_provider/datafetching/__pycache__/fetch_yahoo.cpython-37.pyc
pandas_ml_quant_data_provider/datafetching/__pycache__/fetch_yahoo.cpython-38.pyc
pandas_ml_quant_data_provider/datafetching/__pycache__/read_ts_file.cpython-37.pyc
pandas_ml_quant_data_provider/datafetching/__pycache__/read_ts_file.cpython-38.pyc
