Metadata-Version: 2.1
Name: pandas-ml-quant-data-provider
Version: 0.1.15
Summary: Augment pandas DataFrame with methods to fetch time series data for quant finance
Home-page: https://github.com/KIC/pandas-ml-quant
Author: KIC
Author-email: 
License: MIT
Keywords: pandas,ml,util,quant,data,timeseries
Platform: UNKNOWN
Classifier: Development Status :: 3 - Alpha
Classifier: Intended Audience :: Developers
Classifier: Topic :: Software Development :: Build Tools
Classifier: License :: OSI Approved :: MIT License
Classifier: Programming Language :: Python :: 3
Classifier: Programming Language :: Python :: 3.7
Provides-Extra: dev
